kessho/__init__.py
kessho/batch/__init__.py
kessho/batch/create_flr.py
kessho/batch/create_rema.py
kessho/batch/create_thfp.py
kessho/datasources/__init__.py
kessho/datasources/bqdata.py
kessho/datasources/etfdb.py
kessho/datasources/finnhub.py
kessho/datasources/first_rate.py
kessho/datasources/forex.py
kessho/datasources/processing.py
kessho/datasources/quandlapi.py
kessho/datasources/tools.py
kessho/datasources/yahoo.py
kessho/datasources/tests/__init__.py
kessho/datasources/tests/test_processing.py
kessho/experiments/__init__.py
kessho/experiments/exp_1_1.py
kessho/features/__init__.py
kessho/features/semantics.py
kessho/features/x11.py
kessho/models/__init__.py
kessho/models/multi_signal.py
kessho/portfolio/__init__.py
kessho/portfolio/efinance.py
kessho/portfolio/tests.py
kessho/portfolio/time_series.py
kessho/portfolio/tools.py
kessho/portfolio/tests/__init__.py
kessho/portfolio/tests/forex.py
kessho/portfolio/tests/test_efinance.py
kessho/settings/__init__.py
kessho/settings/experiment_1_1.py
kessho/settings/series_1.py
sample/__init__.py
sample/simple.py
kessho-0.0.6.dist-info/LICENSE.txt
kessho-0.0.6.dist-info/METADATA
kessho-0.0.6.dist-info/WHEEL
kessho-0.0.6.dist-info/top_level.txt
kessho-0.0.6.dist-info/RECORD
