Metadata-Version: 2.1
Name: kessho
Version: 0.0.6
Summary: Tools for data-driven investing
Home-page: https://github.com/Project-Ellie/kessho
Author: Wolfgang Giersche
Author-email: wgiersche@gmail.com
License: UNKNOWN
Project-URL: Source, https://github.com/Project-Ellie/kessho
Keywords: investing,finance
Platform: UNKNOWN
Classifier: Development Status :: 3 - Alpha
Classifier: Intended Audience :: Developers
Classifier: Topic :: Software Development :: Build Tools
Classifier: License :: OSI Approved :: MIT License
Classifier: Programming Language :: Python :: 3
Classifier: Programming Language :: Python :: 3.6
Classifier: Programming Language :: Python :: 3.7
Classifier: Programming Language :: Python :: 3.8
Classifier: Programming Language :: Python :: 3.9
Classifier: Programming Language :: Python :: 3 :: Only
Requires-Python: >=3.6, <4
License-File: LICENSE.txt
Requires-Dist: peppercorn
Provides-Extra: dev
Requires-Dist: check-manifest ; extra == 'dev'
Provides-Extra: test
Requires-Dist: coverage ; extra == 'test'
